rov_collector/__init__.py
rov_collector/__main__.py
rov_collector/py.typed
rov_collector/rov_collector.py
rov_collector/collectors/__init__.py
rov_collector/collectors/apnic_collector.py
rov_collector/collectors/friends_collector.py
rov_collector/collectors/is_bgp_safe_yet_collector.py
rov_collector/collectors/rov_rpki_net_collector.py
rov_collector/collectors/rovista_collector.py
rov_collector/collectors/tma_collector.py
rov_collector/data/friends.json
rov_collector/data/rov.rpki.net.json
rov_collector/data/tma.csv
rov_collector/graphs/__init__.py
rov_collector/graphs/rov_confidence_distribution_graph.py
rov_collector/graphs/rov_source_graph.py
rov_collector/shared/__init__.py
rov_collector/shared/constants.py
rov_collector/shared/enums.py
rov_collector/shared/rov_info.py
rov_collector/tests/__init__.py
rov_collector/tests/test_rov_collectors.py
rov_collector-1.1.16.dist-info/licenses/LICENSE.txt
rov_collector-1.1.16.dist-info/METADATA
rov_collector-1.1.16.dist-info/WHEEL
rov_collector-1.1.16.dist-info/entry_points.txt
rov_collector-1.1.16.dist-info/top_level.txt
rov_collector-1.1.16.dist-info/RECORD
